LICENSE
MANIFEST.in
README.rst
setup.cfg
setup.py
packagetrack/__init__.py
packagetrack/data.py
packagetrack/fedex.py
packagetrack/ups.py
packagetrack/usps.py
packagetrack/xml_dict.py
packagetrack.egg-info/PKG-INFO
packagetrack.egg-info/SOURCES.txt
packagetrack.egg-info/dependency_links.txt
packagetrack.egg-info/not-zip-safe
packagetrack.egg-info/top_level.txt
packagetrack/tests/__init__.py
packagetrack/tests/test_tracking_info.py
packagetrack/tests/test_xml_dict.py