Metadata-Version: 1.0
Name: packagetrack
Version: 0.2
Summary: Track packages.
Home-page: http://github.com/storborg/packagetrack
Author: Scott Torborg
Author-email: storborg@mit.edu
License: GPL
Keywords: track packages ups fedex usps shipping
Platform: UNKNOWN
Classifier: Development Status :: 3 - Alpha
Classifier: License :: OSI Approved :: GNU General Public License (GPL)
Classifier: Intended Audience :: Developers
Classifier: Natural Language :: English
Classifier: Programming Language :: Python
